examplepackagenishka/__init__.py
examplepackagenishka/example.py
examplepackagenishka/data/sample_data.csv
addonenishka-0.3.2.dist-info/LICENSE
addonenishka-0.3.2.dist-info/METADATA
addonenishka-0.3.2.dist-info/WHEEL
addonenishka-0.3.2.dist-info/entry_points.txt
addonenishka-0.3.2.dist-info/top_level.txt
addonenishka-0.3.2.dist-info/RECORD
