Metadata-Version: 2.1
Name: addonenishka
Version: 0.3.2
Summary: Add one example package.
Home-page: https://github.com/NishkaArora/packagingtutorial
Author: Nishka Arora
Author-email: naarora@caltech.edu
License: UNKNOWN
Platform: UNKNOWN
Classifier: Programming Language :: Python :: 3
Classifier: License :: OSI Approved :: MIT License
Classifier: Operating System :: OS Independent
Requires-Python: >=3.6
License-File: LICENSE
Requires-Dist: pandas
Requires-Dist: numpy
Requires-Dist: tabulate
